dexray_intercept/__init__.py
dexray_intercept/about.py
dexray_intercept/ammm.py
dexray_intercept/appProfiling.py
dexray_intercept/appProfiling_legacy.py
dexray_intercept/compatibility.py
dexray_intercept/deviceUtils.py
dexray_intercept/parser.py
dexray_intercept/parser_legacy.py
dexray_intercept/profiling.js
dexray_intercept/resultManager.py
dexray_intercept/formatters/__init__.py
dexray_intercept/formatters/base.py
dexray_intercept/formatters/console.py
dexray_intercept/formatters/factory.py
dexray_intercept/formatters/json_formatter.py
dexray_intercept/models/__init__.py
dexray_intercept/models/events.py
dexray_intercept/models/profile.py
dexray_intercept/parsers/__init__.py
dexray_intercept/parsers/base.py
dexray_intercept/parsers/bypass.py
dexray_intercept/parsers/crypto.py
dexray_intercept/parsers/database.py
dexray_intercept/parsers/dex.py
dexray_intercept/parsers/factory.py
dexray_intercept/parsers/filesystem.py
dexray_intercept/parsers/ipc.py
dexray_intercept/parsers/network.py
dexray_intercept/parsers/process.py
dexray_intercept/parsers/services.py
dexray_intercept/services/__init__.py
dexray_intercept/services/cert_pinning.py
dexray_intercept/services/hook_manager.py
dexray_intercept/services/instrumentation.py
dexray_intercept/services/mitmproxy_manager.py
dexray_intercept/services/profile_collector.py
dexray_intercept/utils/__init__.py
dexray_intercept/utils/android_utils.py
dexray_intercept/utils/crypto_utils.py
dexray_intercept/utils/event_logger.py
dexray_intercept/utils/hexdump.py
dexray_intercept/utils/string_utils.py
dexray_intercept-1.0.1.9.dist-info/licenses/LICENSE
dexray_intercept-1.0.1.9.dist-info/METADATA
dexray_intercept-1.0.1.9.dist-info/WHEEL
dexray_intercept-1.0.1.9.dist-info/entry_points.txt
dexray_intercept-1.0.1.9.dist-info/top_level.txt
dexray_intercept-1.0.1.9.dist-info/RECORD
