Metadata-Version: 2.4
Name: dexray-intercept
Version: 1.0.1.9
Summary: Part of the Sandroid dynamic sandbox: creates runtime profiles to track Android app behavior using Frida.
Home-page: https://github.com/fkie-cad/Sandroid_Dexray-Intercept
Author: Daniel Baier, Jan-Niclas Hilgert
Author-email: daniel.baier@fkie.fraunhofer.de
License: GPL-3.0-only
Project-URL: Source, https://github.com/fkie-cad/Sandroid_Dexray-Intercept
Project-URL: Issues, https://github.com/fkie-cad/Sandroid_Dexray-Intercept/issues
Project-URL: Documentation, https://fkie-cad.github.io/Sandroid_Dexray-Intercept/
Keywords: mobile,instrumentation,frida,hook,android
Classifier: License :: OSI Approved :: GNU General Public License v3 (GPLv3)
Classifier: Operating System :: OS Independent
Classifier: Natural Language :: English
Classifier: Programming Language :: Python :: 3 :: Only
Classifier: Programming Language :: Python :: 3.8
Classifier: Programming Language :: Python :: 3.9
Classifier: Programming Language :: Python :: 3.10
Classifier: Programming Language :: Python :: 3.11
Classifier: Programming Language :: Python :: 3.12
Classifier: Programming Language :: JavaScript
Classifier: Topic :: Security
Classifier: Topic :: Software Development :: Debuggers
Requires-Python: >=3.8
License-File: LICENSE
Requires-Dist: frida>=15.0.0
Requires-Dist: frida-tools>=11.0.0
Requires-Dist: AndroidFridaManager>=1.8.3
Requires-Dist: cxxfilt
Requires-Dist: fritap
Requires-Dist: mitmproxy
Dynamic: author
Dynamic: author-email
Dynamic: classifier
Dynamic: description
Dynamic: description-content-type
Dynamic: home-page
Dynamic: keywords
Dynamic: license
Dynamic: license-file
Dynamic: project-url
Dynamic: requires-dist
Dynamic: requires-python
Dynamic: summary
